steganossaurus/__init__.py
steganossaurus/__main__.py
steganossaurus/binary_manipulation.py
steganossaurus/handlers.py
steganossaurus/utils.py
steganossaurus-0.2.0.dist-info/entry_points.txt
steganossaurus-0.2.0.dist-info/LICENSE
steganossaurus-0.2.0.dist-info/WHEEL
steganossaurus-0.2.0.dist-info/METADATA
steganossaurus-0.2.0.dist-info/RECORD
